{"http_transparent": [{"anonymity": "transparent", "host": "3.211.17.212", "from": "proxylist", "port": 80, "country": "US", "response_time": 0.78, "type": "http"}, {"anonymity": "transparent", "host": "104.131.109.98", "from": "proxylist", "port": 3128, "country": "US", "response_time": 0.87, "type": "http"}, {"anonymity": "transparent", "host": "35.228.49.185", "from": "freeproxylist", "port": 3128, "country": "FI", "response_time": 0.72, "type": "http"}], "https_high_anonymous": [{"anonymity": "high_anonymous", "host": "104.131.109.98", "from": "proxylist", "port": 3128, "country": "US", "response_time": 0.94, "type": "https"}], "http_high_anonymous": [{"anonymity": "high_anonymous", "host": "80.48.119.28", "from": "freeproxylist", "port": 8080, "country": "PL", "response_time": 0.99, "type": "http"}, {"anonymity": "high_anonymous", "host": "169.57.1.85", "from": "freeproxylist", "port": 8123, "country": "MX", "response_time": 0.79, "type": "http"}, {"anonymity": "high_anonymous", "host": "164.92.215.166", "from": "freeproxylist", "port": 8080, "country": "US", "response_time": 0.86, "type": "http"}, {"anonymity": "high_anonymous", "host": "81.4.102.223", "from": "freeproxylist", "port": 8081, "country": "NL", "response_time": 0.87, "type": "http"}]}