{"http_high_anonymous": [{"country": "US", "host": "165.154.235.76", "port": 80, "from": "freeproxylist", "type": "http", "response_time": 0.93, "anonymity": "high_anonymous"}, {"country": "MX", "host": "169.57.1.85", "port": 8123, "from": "freeproxylist", "type": "http", "response_time": 0.99, "anonymity": "high_anonymous"}, {"country": "US", "host": "20.110.214.83", "port": 80, "from": "freeproxylist", "type": "http", "response_time": 0.95, "anonymity": "high_anonymous"}, {"country": "BR", "host": "20.206.121.30", "port": 8000, "from": "freeproxylist", "type": "http", "response_time": 0.65, "anonymity": "high_anonymous"}]}