{"http_high_anonymous": [{"from": "freeproxylist", "country": "US", "response_time": 0.96, "port": 8080, "anonymity": "high_anonymous", "type": "http", "host": "164.92.76.77"}, {"from": "proxylist", "country": "CN", "response_time": 0.88, "port": 8081, "anonymity": "high_anonymous", "type": "http", "host": "182.92.77.108"}, {"from": "proxylist", "country": "SG", "response_time": 0.87, "port": 8000, "anonymity": "high_anonymous", "type": "http", "host": "18.140.166.66"}], "http_transparent": [{"from": "proxylist", "country": "GB", "response_time": 0.53, "port": 80, "anonymity": "transparent", "type": "http", "host": "185.237.98.85"}, {"from": "proxylist", "country": "US", "response_time": 0.83, "port": 80, "anonymity": "transparent", "type": "http", "host": "47.89.153.213"}]}