{"https_high_anonymous": [{"anonymity": "high_anonymous", "type": "https", "host": "45.195.76.130", "port": 999, "country": "DO", "response_time": 0.93, "from": "proxylist"}], "http_high_anonymous": [{"anonymity": "high_anonymous", "type": "http", "host": "159.197.250.134", "port": 3128, "country": "US", "response_time": 0.89, "from": "freeproxylist"}, {"anonymity": "high_anonymous", "type": "http", "host": "65.20.152.46", "port": 8080, "country": "IQ", "response_time": 0.83, "from": "proxylist"}], "http_transparent": [{"anonymity": "transparent", "type": "http", "host": "3.6.28.158", "port": 1521, "country": "IN", "response_time": 0.65, "from": "proxylist"}, {"anonymity": "transparent", "type": "http", "host": "45.195.76.130", "port": 999, "country": "DO", "response_time": 0.47, "from": "proxylist"}], "http_anonymous": [{"anonymity": "anonymous", "type": "http", "host": "208.113.134.223", "port": 80, "country": "US", "response_time": 0.11, "from": "freeproxylist"}]}