{"http_high_anonymous": [{"country": "US", "response_time": 0.99, "anonymity": "high_anonymous", "type": "http", "port": 80, "from": "proxylist", "host": "54.200.36.47"}, {"country": "MX", "response_time": 0.2, "anonymity": "high_anonymous", "type": "http", "port": 8123, "from": "freeproxylist", "host": "169.57.1.85"}, {"country": "DE", "response_time": 0.47, "anonymity": "high_anonymous", "type": "http", "port": 8888, "from": "freeproxylist", "host": "49.12.191.178"}, {"country": "SG", "response_time": 0.64, "anonymity": "high_anonymous", "type": "http", "port": 8080, "from": "freeproxylist", "host": "139.99.88.19"}], "https_high_anonymous": [{"country": "MX", "response_time": 0.62, "anonymity": "high_anonymous", "type": "https", "port": 8123, "from": "freeproxylist", "host": "169.57.1.85"}, {"country": "US", "response_time": 0.39, "anonymity": "high_anonymous", "type": "https", "port": 3128, "from": "freeproxylist", "host": "18.118.139.123"}], "http_anonymous": [{"country": "US", "response_time": 0.14, "anonymity": "anonymous", "type": "http", "port": 3128, "from": "freeproxylist", "host": "18.118.139.123"}]}