{"https_high_anonymous": [{"host": "52.45.107.168", "port": 80, "from": "freeproxylist", "anonymity": "high_anonymous", "response_time": 0.9, "country": "US", "type": "https"}, {"host": "80.69.77.115", "port": 8007, "from": "proxylist", "anonymity": "high_anonymous", "response_time": 0.96, "country": "NL", "type": "https"}], "http_transparent": [{"host": "3.211.17.212", "port": 80, "from": "proxylist", "anonymity": "transparent", "response_time": 0.92, "country": "US", "type": "http"}, {"host": "157.100.12.138", "port": 999, "from": "freeproxylist", "anonymity": "transparent", "response_time": 0.77, "country": "EC", "type": "http"}, {"host": "47.252.4.64", "port": 8888, "from": "proxylist", "anonymity": "transparent", "response_time": 0.86, "country": "US", "type": "http"}, {"host": "80.69.77.115", "port": 8007, "from": "proxylist", "anonymity": "transparent", "response_time": 0.36, "country": "NL", "type": "http"}, {"host": "47.89.185.178", "port": 8888, "from": "proxylist", "anonymity": "transparent", "response_time": 0.47, "country": "US", "type": "http"}, {"host": "185.237.98.85", "port": 80, "from": "proxylist", "anonymity": "transparent", "response_time": 0.5, "country": "GB", "type": "http"}, {"host": "94.23.241.200", "port": 3128, "from": "proxylist", "anonymity": "transparent", "response_time": 0.88, "country": "FR", "type": "http"}]}