{"http_high_anonymous": [{"country": "NL", "port": 80, "host": "194.5.193.183", "type": "http", "response_time": 0.98, "anonymity": "high_anonymous", "from": "txt"}, {"country": "MX", "port": 80, "host": "169.57.1.84", "type": "http", "response_time": 0.76, "anonymity": "high_anonymous", "from": "freeproxylist"}, {"country": "US", "port": 80, "host": "107.151.182.247", "type": "http", "response_time": 0.78, "anonymity": "high_anonymous", "from": "freeproxylist"}, {"country": "CL", "port": 3128, "host": "129.151.117.180", "type": "http", "response_time": 0.93, "anonymity": "high_anonymous", "from": "freeproxylist"}, {"country": "UA", "port": 8081, "host": "178.54.21.203", "type": "http", "response_time": 0.91, "anonymity": "high_anonymous", "from": "freeproxylist"}, {"country": "KR", "port": 8080, "host": "14.53.72.89", "type": "http", "response_time": 0.85, "anonymity": "high_anonymous", "from": "freeproxylist"}], "http_transparent": [{"country": "US", "port": 80, "host": "3.211.17.212", "type": "http", "response_time": 0.84, "anonymity": "transparent", "from": "proxylist"}, {"country": "US", "port": 3129, "host": "198.255.17.202", "type": "http", "response_time": 0.17, "anonymity": "transparent", "from": "freeproxylist"}], "https_high_anonymous": [{"country": "US", "port": 3129, "host": "198.255.17.202", "type": "https", "response_time": 0.48, "anonymity": "high_anonymous", "from": "freeproxylist"}]}