{"http_transparent": [{"type": "http", "anonymity": "transparent", "host": "3.211.17.212", "country": "US", "port": 80, "from": "proxylist", "response_time": 0.86}, {"type": "http", "anonymity": "transparent", "host": "189.165.30.98", "country": "MX", "port": 10101, "from": "proxylist", "response_time": 0.97}], "http_high_anonymous": [{"type": "http", "anonymity": "high_anonymous", "host": "51.81.80.44", "country": "US", "port": 80, "from": "proxylist", "response_time": 0.82}, {"type": "http", "anonymity": "high_anonymous", "host": "34.233.73.65", "country": "US", "port": 8080, "from": "freeproxylist", "response_time": 0.65}, {"type": "http", "anonymity": "high_anonymous", "host": "107.151.182.247", "country": "US", "port": 80, "from": "freeproxylist", "response_time": 0.96}, {"type": "http", "anonymity": "high_anonymous", "host": "195.168.98.98", "country": "SK", "port": 8000, "from": "freeproxylist", "response_time": 0.98}]}