{"https_high_anonymous": [{"type": "https", "anonymity": "high_anonymous", "response_time": 0.96, "host": "34.203.226.164", "country": "US", "port": 80, "from": "freeproxylist"}], "http_high_anonymous": [{"type": "http", "anonymity": "high_anonymous", "response_time": 0.71, "host": "34.203.226.164", "country": "US", "port": 80, "from": "freeproxylist"}, {"type": "http", "anonymity": "high_anonymous", "response_time": 0.76, "host": "195.80.49.237", "country": "RU", "port": 80, "from": "freeproxylist"}, {"type": "http", "anonymity": "high_anonymous", "response_time": 0.77, "host": "195.80.49.235", "country": "RU", "port": 80, "from": "freeproxylist"}, {"type": "http", "anonymity": "high_anonymous", "response_time": 0.79, "host": "169.57.1.85", "country": "MX", "port": 8123, "from": "freeproxylist"}, {"type": "http", "anonymity": "high_anonymous", "response_time": 0.68, "host": "23.94.98.201", "country": "US", "port": 8080, "from": "freeproxylist"}, {"type": "http", "anonymity": "high_anonymous", "response_time": 0.95, "host": "47.254.16.71", "country": "US", "port": 5008, "from": "proxylist"}], "http_transparent": [{"type": "http", "anonymity": "transparent", "response_time": 0.88, "host": "3.211.17.212", "country": "US", "port": 80, "from": "proxylist"}]}