{"http_high_anonymous": [{"country": "US", "from": "freeproxylist", "port": 80, "type": "http", "anonymity": "high_anonymous", "response_time": 0.72, "host": "45.56.84.125"}, {"country": null, "from": "freeproxylist", "port": 1080, "type": "http", "anonymity": "high_anonymous", "response_time": 0.81, "host": "85.195.86.234"}], "http_transparent": [{"country": "US", "from": "proxylist", "port": 80, "type": "http", "anonymity": "transparent", "response_time": 0.83, "host": "3.211.17.212"}, {"country": "US", "from": "proxylist", "port": 3128, "type": "http", "anonymity": "transparent", "response_time": 0.86, "host": "172.96.114.86"}]}