{"http_transparent": [{"type": "http", "anonymity": "transparent", "host": "165.16.60.1", "country": "LY", "response_time": 0.97, "from": "proxylist", "port": 8080}, {"type": "http", "anonymity": "transparent", "host": "186.233.186.60", "country": "US", "response_time": 0.3, "from": "proxylist", "port": 8080}, {"type": "http", "anonymity": "transparent", "host": "20.234.85.50", "country": "US", "response_time": 0.64, "from": "proxylist", "port": 3128}, {"type": "http", "anonymity": "transparent", "host": "187.72.243.90", "country": "BR", "response_time": 0.68, "from": "proxylist", "port": 3128}, {"type": "http", "anonymity": "transparent", "host": "185.83.144.222", "country": "TR", "response_time": 0.73, "from": "proxylist", "port": 3128}], "https_high_anonymous": [{"type": "https", "anonymity": "high_anonymous", "host": "18.116.172.238", "country": "US", "response_time": 0.61, "from": "proxylist", "port": 3128}], "http_anonymous": [{"type": "http", "anonymity": "anonymous", "host": "18.116.172.238", "country": "US", "response_time": 0.41, "from": "proxylist", "port": 3128}], "http_high_anonymous": [{"type": "http", "anonymity": "high_anonymous", "host": "18.185.58.14", "country": "DE", "response_time": 0.69, "from": "proxylist", "port": 3128}]}