{"http_high_anonymous": [{"host": "45.42.177.50", "response_time": 0.81, "port": 3128, "anonymity": "high_anonymous", "from": "freeproxylist", "country": "US", "type": "http"}, {"host": "165.154.235.76", "response_time": 0.65, "port": 80, "anonymity": "high_anonymous", "from": "freeproxylist", "country": "US", "type": "http"}, {"host": "45.42.177.49", "response_time": 0.95, "port": 3128, "anonymity": "high_anonymous", "from": "freeproxylist", "country": "US", "type": "http"}, {"host": "45.42.177.17", "response_time": 0.95, "port": 3128, "anonymity": "high_anonymous", "from": "freeproxylist", "country": "US", "type": "http"}, {"host": "169.57.1.85", "response_time": 0.97, "port": 8123, "anonymity": "high_anonymous", "from": "freeproxylist", "country": "MX", "type": "http"}, {"host": "20.110.214.83", "response_time": 0.91, "port": 80, "anonymity": "high_anonymous", "from": "freeproxylist", "country": "US", "type": "http"}], "http_transparent": [{"host": "206.62.64.34", "response_time": 0.9, "port": 8080, "anonymity": "transparent", "from": "freeproxylist", "country": "BR", "type": "http"}]}