{"http_transparent": [{"host": "3.211.17.212", "from": "proxylist", "type": "http", "country": "US", "anonymity": "transparent", "port": 80, "response_time": 0.88}, {"host": "141.94.37.248", "from": "freeproxylist", "type": "http", "country": "FR", "anonymity": "transparent", "port": 3128, "response_time": 0.47}, {"host": "181.119.64.35", "from": "freeproxylist", "type": "http", "country": "AR", "anonymity": "transparent", "port": 999, "response_time": 0.53}], "https_high_anonymous": [{"host": "152.70.193.57", "from": "freeproxylist", "type": "https", "country": "US", "anonymity": "high_anonymous", "port": 59394, "response_time": 0.25}], "http_high_anonymous": [{"host": "194.5.193.183", "from": "txt", "type": "http", "country": "NL", "anonymity": "high_anonymous", "port": 80, "response_time": 0.97}, {"host": "190.152.5.17", "from": "freeproxylist", "type": "http", "country": "EC", "anonymity": "high_anonymous", "port": 39888, "response_time": 0.99}, {"host": "128.199.13.74", "from": "freeproxylist", "type": "http", "country": "US", "anonymity": "high_anonymous", "port": 80, "response_time": 0.21}, {"host": "152.70.193.57", "from": "freeproxylist", "type": "http", "country": "US", "anonymity": "high_anonymous", "port": 59394, "response_time": 0.1}]}