{"http_transparent": [{"from": "proxylist", "type": "http", "response_time": 0.85, "port": 3128, "host": "14.17.106.202", "anonymity": "transparent", "country": "CN"}, {"from": "proxylist", "type": "http", "response_time": 0.53, "port": 80, "host": "185.237.98.85", "anonymity": "transparent", "country": "GB"}], "http_high_anonymous": [{"from": "proxylist", "type": "http", "response_time": 0.94, "port": 1081, "host": "151.248.122.52", "anonymity": "high_anonymous", "country": "RU"}, {"from": "proxylist", "type": "http", "response_time": 0.85, "port": 80, "host": "188.254.0.59", "anonymity": "high_anonymous", "country": "RU"}, {"from": "proxylist", "type": "http", "response_time": 0.9, "port": 22, "host": "123.56.3.229", "anonymity": "high_anonymous", "country": "CN"}, {"from": "proxylist", "type": "http", "response_time": 0.9, "port": 30001, "host": "183.247.194.229", "anonymity": "high_anonymous", "country": "CN"}, {"from": "proxylist", "type": "http", "response_time": 0.87, "port": 30001, "host": "39.175.90.51", "anonymity": "high_anonymous", "country": "CN"}, {"from": "proxylist", "type": "http", "response_time": 0.89, "port": 30001, "host": "39.175.89.223", "anonymity": "high_anonymous", "country": "CN"}]}