{"http_high_anonymous": [{"from": "freeproxylist", "country": "MX", "host": "169.57.1.85", "anonymity": "high_anonymous", "type": "http", "port": 8123, "response_time": 0.98}, {"from": "freeproxylist", "country": "US", "host": "20.119.204.44", "anonymity": "high_anonymous", "type": "http", "port": 8000, "response_time": 0.71}, {"from": "freeproxylist", "country": "US", "host": "20.228.217.236", "anonymity": "high_anonymous", "type": "http", "port": 8000, "response_time": 0.83}, {"from": "freeproxylist", "country": "US", "host": "40.122.232.169", "anonymity": "high_anonymous", "type": "http", "port": 8000, "response_time": 0.95}, {"from": "freeproxylist", "country": "US", "host": "40.122.224.41", "anonymity": "high_anonymous", "type": "http", "port": 8000, "response_time": 0.74}], "https_high_anonymous": [{"from": "freeproxylist", "country": "US", "host": "40.122.224.41", "anonymity": "high_anonymous", "type": "https", "port": 8000, "response_time": 0.94}]}