{"http_high_anonymous": [{"type": "http", "anonymity": "high_anonymous", "from": "proxylist", "response_time": 0.88, "country": "CN", "port": 30001, "host": "39.175.92.205"}, {"type": "http", "anonymity": "high_anonymous", "from": "proxylist", "response_time": 0.87, "country": "CN", "port": 30001, "host": "183.247.211.157"}, {"type": "http", "anonymity": "high_anonymous", "from": "proxylist", "response_time": 0.99, "country": "CN", "port": 22, "host": "60.205.191.111"}], "http_transparent": [{"type": "http", "anonymity": "transparent", "from": "proxylist", "response_time": 0.9, "country": "US", "port": 80, "host": "3.211.17.212"}, {"type": "http", "anonymity": "transparent", "from": "proxylist", "response_time": 0.85, "country": "CN", "port": 8888, "host": "112.124.4.35"}, {"type": "http", "anonymity": "transparent", "from": "proxylist", "response_time": 0.43, "country": "US", "port": 3128, "host": "167.172.239.13"}, {"type": "http", "anonymity": "transparent", "from": "proxylist", "response_time": 0.61, "country": "EG", "port": 1981, "host": "41.65.36.165"}], "https_high_anonymous": [{"type": "https", "anonymity": "high_anonymous", "from": "proxylist", "response_time": 0.62, "country": "US", "port": 3128, "host": "167.172.239.13"}]}