{"http_transparent": [{"type": "http", "host": "163.172.215.211", "country": "NL", "from": "proxylist", "anonymity": "transparent", "port": 3128, "response_time": 0.4}, {"type": "http", "host": "122.155.165.191", "country": "TH", "from": "proxylist", "anonymity": "transparent", "port": 3128, "response_time": 0.76}, {"type": "http", "host": "208.52.180.80", "country": "US", "from": "proxylist", "anonymity": "transparent", "port": 5555, "response_time": 0.22}, {"type": "http", "host": "85.14.243.31", "country": "DE", "from": "proxylist", "anonymity": "transparent", "port": 3128, "response_time": 0.45}], "http_high_anonymous": [{"type": "http", "host": "20.110.214.83", "country": "US", "from": "freeproxylist", "anonymity": "high_anonymous", "port": 80, "response_time": 0.82}, {"type": "http", "host": "46.151.105.34", "country": "RU", "from": "proxylist", "anonymity": "high_anonymous", "port": 8081, "response_time": 0.5}, {"type": "http", "host": "20.230.193.232", "country": "US", "from": "proxylist", "anonymity": "high_anonymous", "port": 80, "response_time": 0.52}]}