{"https_high_anonymous": [{"from": "freeproxylist", "host": "18.118.139.123", "country": "US", "type": "https", "anonymity": "high_anonymous", "response_time": 0.93, "port": 3128}], "http_high_anonymous": [{"from": "freeproxylist", "host": "103.206.20.105", "country": "HK", "type": "http", "anonymity": "high_anonymous", "response_time": 0.61, "port": 8000}, {"from": "freeproxylist", "host": "23.238.33.186", "country": "US", "type": "http", "anonymity": "high_anonymous", "response_time": 0.86, "port": 80}, {"from": "freeproxylist", "host": "49.12.191.178", "country": "DE", "type": "http", "anonymity": "high_anonymous", "response_time": 0.53, "port": 8888}, {"from": "freeproxylist", "host": "80.179.140.189", "country": "IL", "type": "http", "anonymity": "high_anonymous", "response_time": 0.61, "port": 80}], "http_anonymous": [{"from": "freeproxylist", "host": "18.118.139.123", "country": "US", "type": "http", "anonymity": "anonymous", "response_time": 0.74, "port": 3128}]}