{"https_high_anonymous": [{"from": "proxylist", "type": "https", "anonymity": "high_anonymous", "host": "186.233.186.60", "port": 8080, "country": "US", "response_time": 0.65}], "http_transparent": [{"from": "proxylist", "type": "http", "anonymity": "transparent", "host": "118.190.244.234", "port": 3128, "country": "CN", "response_time": 0.64}, {"from": "proxylist", "type": "http", "anonymity": "transparent", "host": "167.172.239.13", "port": 3128, "country": "US", "response_time": 0.86}, {"from": "proxylist", "type": "http", "anonymity": "transparent", "host": "122.155.165.191", "port": 3128, "country": "TH", "response_time": 0.84}, {"from": "proxylist", "type": "http", "anonymity": "transparent", "host": "103.180.149.1", "port": 3128, "country": "unknown", "response_time": 0.98}], "http_high_anonymous": [{"from": "freeproxylist", "type": "http", "anonymity": "high_anonymous", "host": "164.92.76.77", "port": 8080, "country": "US", "response_time": 0.69}, {"from": "freeproxylist", "type": "http", "anonymity": "high_anonymous", "host": "206.81.0.107", "port": 80, "country": "US", "response_time": 0.54}, {"from": "proxylist", "type": "http", "anonymity": "high_anonymous", "host": "183.247.194.203", "port": 30001, "country": "CN", "response_time": 0.83}, {"from": "proxylist", "type": "http", "anonymity": "high_anonymous", "host": "47.105.54.91", "port": 3128, "country": "CN", "response_time": 0.87}]}