{"http_high_anonymous": [{"from": "freeproxylist", "host": "169.57.1.85", "anonymity": "high_anonymous", "port": 8123, "type": "http", "response_time": 0.69, "country": "MX"}, {"from": "freeproxylist", "host": "95.59.26.129", "anonymity": "high_anonymous", "port": 80, "type": "http", "response_time": 0.86, "country": "KZ"}, {"from": "freeproxylist", "host": "65.21.190.58", "anonymity": "high_anonymous", "port": 8888, "type": "http", "response_time": 0.45, "country": "FI"}], "http_anonymous": [{"from": "freeproxylist", "host": "208.113.134.223", "anonymity": "anonymous", "port": 80, "type": "http", "response_time": 0.04, "country": "US"}], "http_transparent": [{"from": "freeproxylist", "host": "84.201.186.253", "anonymity": "transparent", "port": 3128, "type": "http", "response_time": 0.38, "country": "RU"}]}