{"http_transparent": [{"country": "UA", "anonymity": "transparent", "port": 8080, "host": "80.91.163.139", "from": "proxylist", "type": "http", "response_time": 0.56}, {"country": "DE", "anonymity": "transparent", "port": 8081, "host": "217.160.192.11", "from": "proxylist", "type": "http", "response_time": 0.29}, {"country": "SG", "anonymity": "transparent", "port": 3128, "host": "194.233.95.214", "from": "proxylist", "type": "http", "response_time": 0.83}, {"country": "BY", "anonymity": "transparent", "port": 3128, "host": "46.53.191.12", "from": "proxylist", "type": "http", "response_time": 0.46}], "http_high_anonymous": [{"country": "US", "anonymity": "high_anonymous", "port": 80, "host": "20.110.214.83", "from": "freeproxylist", "type": "http", "response_time": 0.97}, {"country": "CN", "anonymity": "high_anonymous", "port": 9091, "host": "58.20.184.187", "from": "proxylist", "type": "http", "response_time": 0.96}]}