{"https_high_anonymous": [{"from": "freeproxylist", "type": "https", "host": "5.161.105.105", "anonymity": "high_anonymous", "country": "DE", "response_time": 0.89, "port": 80}], "http_transparent": [{"from": "proxylist", "type": "http", "host": "157.100.12.138", "anonymity": "transparent", "country": "EC", "response_time": 0.46, "port": 999}, {"from": "proxylist", "type": "http", "host": "173.212.216.104", "anonymity": "transparent", "country": "DE", "response_time": 0.77, "port": 3128}, {"from": "proxylist", "type": "http", "host": "81.181.110.173", "anonymity": "transparent", "country": "RO", "response_time": 0.26, "port": 2019}], "http_high_anonymous": [{"from": "freeproxylist", "type": "http", "host": "5.161.105.105", "anonymity": "high_anonymous", "country": "DE", "response_time": 0.86, "port": 80}, {"from": "proxylist", "type": "http", "host": "222.139.156.118", "anonymity": "high_anonymous", "country": "CN", "response_time": 0.98, "port": 9091}, {"from": "proxylist", "type": "http", "host": "52.188.106.163", "anonymity": "high_anonymous", "country": "US", "response_time": 0.56, "port": 3128}]}