{"http_high_anonymous": [{"anonymity": "high_anonymous", "type": "http", "response_time": 0.74, "from": "freeproxylist", "country": "US", "port": 3128, "host": "208.115.223.133"}, {"anonymity": "high_anonymous", "type": "http", "response_time": 0.79, "from": "freeproxylist", "country": "US", "port": 80, "host": "20.110.214.83"}, {"anonymity": "high_anonymous", "type": "http", "response_time": 0.59, "from": "proxylist", "country": "RU", "port": 81, "host": "188.32.241.34"}, {"anonymity": "high_anonymous", "type": "http", "response_time": 0.48, "from": "proxylist", "country": "PT", "port": 80, "host": "188.82.97.82"}], "http_transparent": [{"anonymity": "transparent", "type": "http", "response_time": 0.28, "from": "proxylist", "country": "US", "port": 5555, "host": "208.52.137.155"}, {"anonymity": "transparent", "type": "http", "response_time": 0.41, "from": "proxylist", "country": "US", "port": 5555, "host": "208.52.180.77"}, {"anonymity": "transparent", "type": "http", "response_time": 0.76, "from": "proxylist", "country": "RU", "port": 8081, "host": "91.215.79.95"}, {"anonymity": "transparent", "type": "http", "response_time": 0.83, "from": "proxylist", "country": "EG", "port": 1981, "host": "62.193.108.133"}, {"anonymity": "transparent", "type": "http", "response_time": 0.91, "from": "proxylist", "country": "CN", "port": 9000, "host": "101.80.86.151"}]}