{"http_high_anonymous": [{"from": "freeproxylist", "response_time": 0.57, "anonymity": "high_anonymous", "country": "US", "host": "51.81.80.44", "type": "http", "port": 80}, {"from": "freeproxylist", "response_time": 0.88, "anonymity": "high_anonymous", "country": "US", "host": "107.151.182.247", "type": "http", "port": 80}, {"from": "freeproxylist", "response_time": 0.5, "anonymity": "high_anonymous", "country": "DE", "host": "138.201.145.164", "type": "http", "port": 8080}], "http_transparent": [{"from": "proxylist", "response_time": 0.96, "anonymity": "transparent", "country": "US", "host": "209.165.163.187", "type": "http", "port": 3128}]}