{"http_high_anonymous": [{"response_time": 0.72, "from": "freeproxylist", "anonymity": "high_anonymous", "country": "US", "type": "http", "host": "103.214.109.66", "port": 80}, {"response_time": 0.9, "from": "freeproxylist", "anonymity": "high_anonymous", "country": "RU", "type": "http", "host": "91.221.17.220", "port": 8000}, {"response_time": 0.96, "from": "freeproxylist", "anonymity": "high_anonymous", "country": "DE", "type": "http", "host": "154.16.202.47", "port": 80}], "http_transparent": [{"response_time": 0.97, "from": "freeproxylist", "anonymity": "transparent", "country": "IE", "type": "http", "host": "176.34.92.229", "port": 9080}, {"response_time": 0.87, "from": "proxylist", "anonymity": "transparent", "country": "RU", "type": "http", "host": "31.192.233.30", "port": 5006}], "https_high_anonymous": [{"response_time": 0.68, "from": "freeproxylist", "anonymity": "high_anonymous", "country": "US", "type": "https", "host": "104.223.88.232", "port": 8118}]}