{"http_transparent": [{"from": "proxylist", "host": "92.49.136.61", "country": "RU", "port": 8081, "response_time": 0.68, "type": "http", "anonymity": "transparent"}, {"from": "proxylist", "host": "185.237.98.85", "country": "GB", "port": 80, "response_time": 0.41, "type": "http", "anonymity": "transparent"}, {"from": "proxylist", "host": "50.205.202.249", "country": "US", "port": 3128, "response_time": 0.74, "type": "http", "anonymity": "transparent"}], "http_high_anonymous": [{"from": "freeproxylist", "host": "167.172.157.96", "country": "US", "port": 80, "response_time": 0.56, "type": "http", "anonymity": "high_anonymous"}, {"from": "proxylist", "host": "58.20.184.187", "country": "CN", "port": 9091, "response_time": 0.91, "type": "http", "anonymity": "high_anonymous"}, {"from": "proxylist", "host": "203.222.25.57", "country": "TW", "port": 80, "response_time": 0.95, "type": "http", "anonymity": "high_anonymous"}]}