{"http_high_anonymous": [{"from": "freeproxylist", "host": "181.129.43.3", "country": "CO", "response_time": 0.97, "anonymity": "high_anonymous", "port": 8080, "type": "http"}, {"from": "freeproxylist", "host": "170.39.116.186", "country": "US", "response_time": 0.71, "anonymity": "high_anonymous", "port": 3128, "type": "http"}, {"from": "freeproxylist", "host": "169.57.1.85", "country": "MX", "response_time": 0.81, "anonymity": "high_anonymous", "port": 8123, "type": "http"}, {"from": "freeproxylist", "host": "165.154.235.76", "country": "US", "response_time": 0.84, "anonymity": "high_anonymous", "port": 80, "type": "http"}, {"from": "proxylist", "host": "103.152.112.145", "country": "US", "response_time": 0.91, "anonymity": "high_anonymous", "port": 80, "type": "http"}, {"from": "freeproxylist", "host": "20.111.54.16", "country": "FR", "response_time": 0.98, "anonymity": "high_anonymous", "port": 80, "type": "http"}, {"from": "freeproxylist", "host": "51.15.242.202", "country": "FR", "response_time": 0.97, "anonymity": "high_anonymous", "port": 8888, "type": "http"}], "https_high_anonymous": [{"from": "freeproxylist", "host": "170.39.116.186", "country": "US", "response_time": 0.9, "anonymity": "high_anonymous", "port": 3128, "type": "https"}]}