{"http_high_anonymous": [{"from": "proxylist", "country": "US", "port": 3128, "anonymity": "high_anonymous", "host": "52.188.106.163", "response_time": 0.95, "type": "http"}, {"from": "freeproxylist", "country": "MX", "port": 8123, "anonymity": "high_anonymous", "host": "169.57.1.85", "response_time": 0.88, "type": "http"}, {"from": "freeproxylist", "country": "US", "port": 80, "anonymity": "high_anonymous", "host": "20.110.214.83", "response_time": 0.86, "type": "http"}, {"from": "freeproxylist", "country": "US", "port": 3128, "anonymity": "high_anonymous", "host": "170.39.194.16", "response_time": 0.9, "type": "http"}, {"from": "freeproxylist", "country": "GB", "port": 8080, "anonymity": "high_anonymous", "host": "185.61.152.137", "response_time": 0.89, "type": "http"}], "http_transparent": [{"from": "freeproxylist", "country": "BY", "port": 3128, "anonymity": "transparent", "host": "46.53.191.60", "response_time": 0.45, "type": "http"}]}