{"http_transparent": [{"country": "DE", "port": 3128, "type": "http", "from": "freeproxylist", "response_time": 0.43, "anonymity": "transparent", "host": "95.111.245.112"}, {"country": "US", "port": 3128, "type": "http", "from": "proxylist", "response_time": 0.54, "anonymity": "transparent", "host": "164.92.131.226"}, {"country": "CO", "port": 999, "type": "http", "from": "proxylist", "response_time": 0.82, "anonymity": "transparent", "host": "177.93.50.106"}, {"country": "EC", "port": 999, "type": "http", "from": "proxylist", "response_time": 0.89, "anonymity": "transparent", "host": "157.100.12.138"}, {"country": "RU", "port": 8081, "type": "http", "from": "proxylist", "response_time": 0.89, "anonymity": "transparent", "host": "109.191.21.64"}, {"country": "TH", "port": 3128, "type": "http", "from": "proxylist", "response_time": 0.98, "anonymity": "transparent", "host": "122.155.165.191"}], "http_anonymous": [{"country": "DE", "port": 80, "type": "http", "from": "proxylist", "response_time": 0.63, "anonymity": "anonymous", "host": "142.93.96.120"}], "http_high_anonymous": [{"country": "CN", "port": 9091, "type": "http", "from": "proxylist", "response_time": 0.95, "anonymity": "high_anonymous", "host": "183.239.62.251"}]}